delearn/__init__.py
delearn-0.0.1.dist-info/LICENSE
delearn-0.0.1.dist-info/METADATA
delearn-0.0.1.dist-info/WHEEL
delearn-0.0.1.dist-info/top_level.txt
delearn-0.0.1.dist-info/RECORD
