Metadata-Version: 2.1
Name: delearn
Version: 0.0.1
Summary: ~ D E L E A R N ~
Home-page: https://github.com/Nelson-iitp/delearn
Author: Nelson.S
Author-email: mail.nelsonsharma@gmail.com
Classifier: License :: OSI Approved :: MIT License
License-File: LICENSE
